<?xml version="1.0" encoding="UTF-8"?>

<pageSetting id="lcyjfp" title="理财业绩分配" type="yjgx" version="1.0.0.0" pid="" desc="标准版"> 
  <database> 
    <targetTable> 
      <relevance> 
        <name>DXGX_YJGX_LC</name>  
        <fields> 
          <field> 
            <name>jyrq</name>  
            <dbType>INTEGER</dbType> 
          </field>  
          <field> 
            <name>lsh</name>  
            <dbType>VARCHAR(30)</dbType> 
          </field>  
          <field> 
            <name>khdxdh</name>  
            <dbType>INTEGER</dbType> 
          </field>  
          <field> 
            <name>qsrq</name>  
            <dbType>INTEGER</dbType> 
          </field>  
          <field> 
            <name>jsrq</name>  
            <dbType>INTEGER</dbType> 
          </field>  
          <field> 
            <name>zlbl</name>  
            <dbType>DECIMAL(19,5)</dbType> 
          </field>  
          <field> 
            <name>gxly</name>  
            <dbType>VARCHAR(2)</dbType> 
          </field>  
          <field> 
            <name>yylsh</name>  
            <dbType>NUMERIC(20)</dbType> 
          </field> 
        </fields> 
      </relevance>  
      <performance> 
        <name>JXDX_LCJYLS</name>  
        <fields> 
          <field> 
            <name>jyrq</name>  
            <dbType>INTEGER</dbType>  
            <isPrimaryKey>true</isPrimaryKey> 
          </field>  
          <field> 
            <name>lsh</name>  
            <dbType>VARCHAR(30)</dbType>  
            <isPrimaryKey>true</isPrimaryKey> 
          </field>  
          <field> 
            <name>jydm</name>  
            <dbType>VARCHAR(8)</dbType>  
            <isPrimaryKey>false</isPrimaryKey> 
          </field>  
          <field> 
            <name>zhdh</name>  
            <dbType>VARCHAR(40)</dbType>  
            <isPrimaryKey>false</isPrimaryKey> 
          </field>  
          <field> 
            <name>khh</name>  
            <dbType>VARCHAR(30)</dbType>  
            <isPrimaryKey>false</isPrimaryKey> 
          </field>  
          <field> 
            <name>khlx</name>  
            <dbType>VARCHAR(2)</dbType>  
            <isPrimaryKey>false</isPrimaryKey> 
          </field>  
          <field> 
            <name>khmc</name>  
            <dbType>VARCHAR(100)</dbType>  
            <isPrimaryKey>false</isPrimaryKey> 
          </field>  
          <field> 
            <name>jgdh</name>  
            <dbType>VARCHAR(10)</dbType>  
            <isPrimaryKey>false</isPrimaryKey> 
          </field>  
          <field> 
            <name>cpdm</name>  
            <dbType>VARCHAR(20)</dbType>  
            <isPrimaryKey>false</isPrimaryKey> 
          </field>  
          <field> 
            <name>cpqx</name>  
            <dbType>VARCHAR(4)</dbType>  
            <isPrimaryKey>false</isPrimaryKey> 
          </field>  
          <field> 
            <name>jyzt</name>  
            <dbType>VARCHAR(2)</dbType>  
            <isPrimaryKey>false</isPrimaryKey> 
          </field>  
          <field> 
            <name>jyqd</name>  
            <dbType>VARCHAR(2)</dbType>  
            <isPrimaryKey>false</isPrimaryKey> 
          </field>  
          <field> 
            <name>bz</name>  
            <dbType>VARCHAR(3)</dbType>  
            <isPrimaryKey>false</isPrimaryKey> 
          </field>  
          <field> 
            <name>jyje</name>  
            <dbType>DECIMAL(25,4)</dbType>  
            <isPrimaryKey>false</isPrimaryKey> 
          </field>  
          <field> 
            <name>jyfs</name>  
            <dbType>DECIMAL(25,4)</dbType>  
            <isPrimaryKey>false</isPrimaryKey> 
          </field>  
          <field> 
            <name>sxf</name>  
            <dbType>DECIMAL(25,4)</dbType>  
            <isPrimaryKey>false</isPrimaryKey> 
          </field>  
          <field> 
            <name>shrq</name>  
            <dbType>INTEGER</dbType>  
            <isPrimaryKey>false</isPrimaryKey> 
          </field>  
          <field> 
            <name>shje</name>  
            <dbType>DECIMAL(25,4)</dbType>  
            <isPrimaryKey>false</isPrimaryKey> 
          </field>  
          <field> 
            <name>hydh</name>  
            <dbType>VARCHAR(12)</dbType>  
            <isPrimaryKey>false</isPrimaryKey> 
          </field>  
          <field> 
            <name>khdxdh</name>  
            <dbType>INTEGER</dbType>  
            <isPrimaryKey>false</isPrimaryKey> 
          </field> 
        </fields>  
        <dateField>jyrq</dateField>  
        <innerFields> 
          <innerField>jyrq</innerField>  
          <innerField>lsh</innerField> 
        </innerFields> 
      </performance>  
      <log> 
        <name>XTB_HYGXRZ_LC</name>  
        <fields> 
          <field> 
            <name>jldh</name>  
            <dbType>INTEGER</dbType> 
          </field>  
          <field> 
            <name>jlsj</name>  
            <dbType>TIMESTAMP</dbType> 
          </field>  
          <field> 
            <name>czlx</name>  
            <dbType>VARCHAR(2)</dbType> 
          </field>  
          <field> 
            <name>xgrdh</name>  
            <dbType>INTEGER</dbType> 
          </field>  
          <field> 
            <name>jyrq</name>  
            <dbType>INTEGER</dbType> 
          </field>  
          <field> 
            <name>lsh</name>  
            <dbType>VARCHAR(30)</dbType> 
          </field> 
        </fields> 
      </log>  
      <record> 
        <name>XTB_HYGXJL_LC</name>  
        <fields> 
          <field> 
            <name>jldh</name>  
            <dbType>INTEGER</dbType> 
          </field>  
          <field> 
            <name>ggbz</name>  
            <dbType>VARCHAR(1)</dbType> 
          </field>  
          <field> 
            <name>khdxdh</name>  
            <dbType>INTEGER</dbType> 
          </field>  
          <field> 
            <name>qsrq</name>  
            <dbType>INTEGER</dbType> 
          </field>  
          <field> 
            <name>jsrq</name>  
            <dbType>INTEGER</dbType> 
          </field>  
          <field> 
            <name>zlbl</name>  
            <dbType>DECIMAL(19,5)</dbType> 
          </field> 
        </fields> 
      </record> 
    </targetTable>  
    <extendTable> 
      <table name="KHDX_JG" alias="KHDX_JG1534818641657" joinType="inner"> 
        <fields> 
          <field> 
            <name>KHDXDH</name>  
            <dbType>INTEGER</dbType> 
          </field>  
          <field> 
            <name>JGDH</name>  
            <dbType>VARCHAR(15)</dbType> 
          </field>  
          <field> 
            <name>JGMC</name>  
            <dbType>VARCHAR(100)</dbType> 
          </field>  
          <field> 
            <name>JYJGBZ</name>  
            <dbType>VARCHAR(1)</dbType> 
          </field>  
          <field> 
            <name>PXBZ</name>  
            <dbType>INTEGER</dbType> 
          </field>  
          <field> 
            <name>ZXZT</name>  
            <dbType>VARCHAR(1)</dbType> 
          </field>  
          <field> 
            <name>ZXRQ</name>  
            <dbType>INTEGER</dbType> 
          </field>  
          <field> 
            <name>FHDH</name>  
            <dbType>VARCHAR(15)</dbType> 
          </field>  
          <field> 
            <name>FHBZ</name>  
            <dbType>VARCHAR(2)</dbType> 
          </field>  
          <field> 
            <name>JGDJ</name>  
            <dbType>VARCHAR(2)</dbType> 
          </field>  
          <field> 
            <name>KYRQ</name>  
            <dbType>INTEGER</dbType> 
          </field> 
        </fields>  
        <relevanceFields> 
          <field> 
            <name>JGDH</name>  
            <dbType/>  
            <operator>=</operator>  
            <condition> 
              <table>JXDX_LCJYLS</table>  
              <field>JGDH</field>  
              <dbType/> 
            </condition>  
            <limitCondition/> 
          </field> 
        </relevanceFields> 
      </table>  
      <table name="CSB_DMMS" alias="CSB_DMMS121" joinType="inner"> 
        <fields> 
          <field> 
            <name>DMMC</name>  
            <dbType>VARCHAR(15)</dbType> 
          </field>  
          <field> 
            <name>DMZ</name>  
            <dbType>VARCHAR(30)</dbType> 
          </field>  
          <field> 
            <name>DMMS</name>  
            <dbType>VARCHAR(200)</dbType> 
          </field>  
          <field> 
            <name>DMSM</name>  
            <dbType>VARCHAR(500)</dbType> 
          </field>  
          <field> 
            <name>XH</name>  
            <dbType>INTEGER</dbType> 
          </field> 
        </fields>  
        <relevanceFields> 
          <field> 
            <name>DMZ</name>  
            <dbType>VARCHAR(30)</dbType>  
            <operator>=</operator>  
            <condition> 
              <table>JXDX_LCJYLS</table>  
              <field>khlx</field>  
              <dbType>VARCHAR(2)</dbType> 
            </condition>  
            <limitCondition>and csb_dmms.dmmc='KHLX'</limitCondition> 
          </field> 
        </relevanceFields> 
      </table>  
      <table name="JXDX_LCCPXX" alias="JXDX_LCCPXX697" joinType="inner"> 
        <fields> 
          <field> 
            <name>CPDM</name>  
            <dbType>VARCHAR(20)</dbType> 
          </field>  
          <field> 
            <name>CPLB</name>  
            <dbType>VARCHAR(2)</dbType> 
          </field>  
          <field> 
            <name>CPMC</name>  
            <dbType>VARCHAR(100)</dbType> 
          </field>  
          <field> 
            <name>MJKSR</name>  
            <dbType>INTEGER</dbType> 
          </field>  
          <field> 
            <name>MJJSR</name>  
            <dbType>INTEGER</dbType> 
          </field>  
          <field> 
            <name>CLRQ</name>  
            <dbType>INTEGER</dbType> 
          </field>  
          <field> 
            <name>JSRQ</name>  
            <dbType>INTEGER</dbType> 
          </field> 
        </fields>  
        <relevanceFields> 
          <field> 
            <name>CPDM</name>  
            <dbType>VARCHAR(20)</dbType>  
            <operator>=</operator>  
            <condition> 
              <table>JXDX_LCJYLS</table>  
              <field>cpdm</field>  
              <dbType>VARCHAR(20)</dbType> 
            </condition>  
            <limitCondition/> 
          </field> 
        </relevanceFields> 
      </table>  
      <table name="CSB_BZ" alias="CSB_BZ425" joinType="inner"> 
        <fields> 
          <field> 
            <name>BZ</name>  
            <dbType>VARCHAR(3)</dbType> 
          </field>  
          <field> 
            <name>BZYWMC</name>  
            <dbType>VARCHAR(30)</dbType> 
          </field>  
          <field> 
            <name>BZZWMC</name>  
            <dbType>VARCHAR(30)</dbType> 
          </field>  
          <field> 
            <name>JXNJS</name>  
            <dbType>SMALLINT</dbType> 
          </field> 
        </fields>  
        <relevanceFields> 
          <field> 
            <name>BZ</name>  
            <dbType>VARCHAR(3)</dbType>  
            <operator>=</operator>  
            <condition> 
              <table>JXDX_LCJYLS</table>  
              <field>bz</field>  
              <dbType>VARCHAR(3)</dbType> 
            </condition>  
            <limitCondition/> 
          </field> 
        </relevanceFields> 
      </table> 
    </extendTable> 
  </database>  
  <mainPart> 
    <tags> 
      <tag name="qsrq" field="JXDX_LCJYLS.jyrq" type="Date" source="perfor" condition="between ? and 1" col="0" row="0" colspan="1"> 
        <attribute key="label" value="交易日期"/>  
        <attribute key="name" value="qsrq"/>  
        <attribute key="dateFmt" value="yyyyMMdd"/>  
        <attribute key="defValType" value="yc"/>  
        <attribute key="styleClass" value=""/>  
        <attribute key="minDate" value="no"/>  
        <attribute key="defVal" value=""/>  
        <attribute key="style" value=""/>  
        <attribute key="isRequired" value="true"/>  
        <attribute key="editable" value="true"/> 
      </tag>  
      <tag name="jsrq" field="JXDX_LCJYLS.jyrq" type="Date" source="perfor" condition="between 1 and ?" col="1" row="0" colspan="1"> 
        <attribute key="label" value="到"/>  
        <attribute key="name" value="jsrq"/>  
        <attribute key="dateFmt" value="yyyyMMdd"/>  
        <attribute key="defValType" value="sysDate"/>  
        <attribute key="styleClass" value=""/>  
        <attribute key="minDate" value="no"/>  
        <attribute key="defVal" value=""/>  
        <attribute key="style" value=""/>  
        <attribute key="isRequired" value="true"/>  
        <attribute key="editable" value="true"/> 
      </tag>  
      <tag name="jgkhdxdh" field="JXDX_LCJYLS.jgdh" type="NewJg" source="perfor" condition="in" col="2" row="0" colspan="1"> 
        <attribute key="label" value="交易机构"/>  
        <attribute key="name" value="jgkhdxdh"/>  
        <attribute key="ckbz" value="jg"/>  
        <attribute key="defVal" value=""/>  
        <attribute key="multiple" value="false"/>  
        <attribute key="cascadeCheck" value="true"/>  
        <attribute key="isRequired" value="true"/>  
        <attribute key="style" value=""/>  
        <attribute key="editable" value="true"/> 
      </tag>  
      <tag name="khlx" field="JXDX_LCJYLS.khlx" type="Dmms" source="perfor" condition="=" col="0" row="1" colspan="1"> 
        <attribute key="label" value="客户类型"/>  
        <attribute key="name" value="khlx"/>  
        <attribute key="dmmc" value="khlx"/>  
        <attribute key="isAll" value="true"/>  
        <attribute key="multiple" value="false"/>  
        <attribute key="defVal" value=""/>  
        <attribute key="width" value="120px;"/>  
        <attribute key="style" value=""/>  
        <attribute key="editable" value="true"/> 
      </tag>  
      <tag name="zhdh" field="JXDX_LCJYLS.zhdh" type="Text" source="perfor" condition="like %?%" col="1" row="1" colspan="1"> 
        <attribute key="label" value="账号"/>  
        <attribute key="name" value="zhdh"/>  
        <attribute key="value" value=""/>  
        <attribute key="maxlength" value=""/>  
        <attribute key="readonly" value="false"/>  
        <attribute key="style" value=""/>  
        <attribute key="styleClass" value=""/>  
        <attribute key="editable" value="true"/> 
      </tag>  
      <tag name="khmc" field="JXDX_LCJYLS.khmc" type="Text" source="perfor" condition="like %?%" col="2" row="1" colspan="1"> 
        <attribute key="label" value="客户名称"/>  
        <attribute key="name" value="khmc"/>  
        <attribute key="value" value=""/>  
        <attribute key="maxlength" value=""/>  
        <attribute key="readonly" value="false"/>  
        <attribute key="style" value=""/>  
        <attribute key="styleClass" value=""/>  
        <attribute key="editable" value="true"/> 
      </tag> 
    </tags>  
    <javascript/> 
  </mainPart>  
  <listPart> 
    <tags> 
      <tag name="label" field="lsh" type="Label" col="0" row="0" condition="=" colspan="1"> 
        <attribute key="label" value="流水号"/>  
        <attribute key="name" value="lsh"/> 
      </tag>  
      <tag name="label" field="zhdh" type="Label" col="1" row="0" condition="=" colspan="1"> 
        <attribute key="label" value="账号"/>  
        <attribute key="name" value="zhdh"/> 
      </tag> 
    </tags>  
    <javascript/> 
  </listPart>  
  <resultSet> 
    <mainTable id="001" title="mainTable" page="true"> 
      <col id="lsh" fieldAlias="lsh" tvalue="JXDX_LCJYLS" tableAlias="JXDX_LCJYLS" source="perfor" title="流水号" align="left" type="string" width="120" format="" exp="true"/>  
      <col id="jyrq" fieldAlias="jyrq" tvalue="JXDX_LCJYLS" tableAlias="JXDX_LCJYLS" source="perfor" title="交易日期" align="left" type="string" width="80" format="" exp="true"/>  
      <col id="JGMC" fieldAlias="JGMC" tvalue="KHDX" tableAlias="KHDX" source="inObject" title="交易机构" align="left" type="string" width="150" format="" exp="true"/>  
      <col id="zhdh" fieldAlias="zhdh" tvalue="JXDX_LCJYLS" tableAlias="JXDX_LCJYLS" source="perfor" title="账号" align="left" type="string" width="120" format="" exp="true"/>  
      <col id="khh" fieldAlias="khh" tvalue="JXDX_LCJYLS" tableAlias="JXDX_LCJYLS" source="perfor" title="客户号" align="left" type="string" width="120" format="" exp="true"/>  
      <col id="khmc" fieldAlias="khmc" tvalue="JXDX_LCJYLS" tableAlias="JXDX_LCJYLS" source="perfor" title="客户名称" align="left" type="string" width="120" format="" exp="true"/>  
      <col id="DMMS" fieldAlias="DMMS" tvalue="CSB_DMMS" tableAlias="CSB_DMMS121" source="extend" title="客户类型" align="left" type="string" width="80" format="" exp="true"/>  
      <col id="cpdm" fieldAlias="cpdm" tvalue="JXDX_LCJYLS" tableAlias="JXDX_LCJYLS" source="perfor" title="产品代码" align="left" type="string" width="120" format="" exp="true"/>  
      <col id="CPMC" fieldAlias="CPMC" tvalue="JXDX_LCCPXX" tableAlias="JXDX_LCCPXX697" source="extend" title="产品名称" align="left" type="string" width="120" format="" exp="true"/>  
      <col id="cpqx" fieldAlias="cpqx" tvalue="JXDX_LCJYLS" tableAlias="JXDX_LCJYLS" source="perfor" title="产品期限" align="left" type="string" width="120" format="" exp="true"/>  
      <col id="shrq" fieldAlias="shrq" tvalue="JXDX_LCJYLS" tableAlias="JXDX_LCJYLS" source="perfor" title="赎回日期" align="left" type="string" width="120" format="" exp="true"/>  
      <col id="DQFPGX" fieldAlias="DQFPGX" tvalue="parentName" tableAlias="parentName" source="base" title="当前分配关系" align="center" type="string" width="200" format="" exp="true"/>  
      <col id="BZZWMC" fieldAlias="BZZWMC" tvalue="CSB_BZ" tableAlias="CSB_BZ425" source="extend" title="币种" align="left" type="string" width="100" format="" exp="true"/>  
      <col id="jyje" fieldAlias="jyje" tvalue="JXDX_LCJYLS" tableAlias="JXDX_LCJYLS" source="perfor" title="交易金额" align="left" type="string" width="120" format="" exp="true"/>  
      <col id="jyfs" fieldAlias="jyfs" tvalue="JXDX_LCJYLS" tableAlias="JXDX_LCJYLS" source="perfor" title="交易份数" align="left" type="string" width="120" format="" exp="true"/> 
    </mainTable>  
    <listTable id="002" type="tag" title="listTable" page="true"> 
      <col id="JGDH" fieldAlias="JGDH" tvalue="KHDX" tableAlias="KHDX" source="inObject" title="机构代号" align="left" type="string" width="100" format=""/>  
      <col id="JGMC" fieldAlias="JGMC" tvalue="KHDX" tableAlias="KHDX" source="inObject" title="机构名称" align="left" type="string" width="150" format=""/>  
      <col id="HYDH" fieldAlias="HYDH" tvalue="KHDX" tableAlias="KHDX" source="inObject" title="行员代号" align="left" type="string" width="80" format=""/>  
      <col id="HYMC" fieldAlias="HYMC" tvalue="KHDX" tableAlias="KHDX" source="inObject" title="行员名称" align="left" type="string" width="90" format=""/>  
      <col id="QSRQ" fieldAlias="QSRQ" tvalue="DXGX_YJGX_LC" tableAlias="DXGX_YJGX_LC" source="rele" title="起始日期" align="left" type="string" width="80" format=""/>  
      <col id="JSRQ" fieldAlias="JSRQ" tvalue="DXGX_YJGX_LC" tableAlias="DXGX_YJGX_LC" source="rele" title="结束日期" align="left" type="string" width="80" format=""/>  
      <col id="ZLBL" fieldAlias="ZLBL" tvalue="DXGX_YJGX_LC" tableAlias="DXGX_YJGX_LC" source="rele" title="增量比例" align="left" type="string" width="80" format=""/> 
    </listTable> 
  </resultSet> 
</pageSetting>
